setup.cfg
setup.py
pyf/__init__.py
pyf.components.consumers.fixedlengthwriter.egg-info/PKG-INFO
pyf.components.consumers.fixedlengthwriter.egg-info/SOURCES.txt
pyf.components.consumers.fixedlengthwriter.egg-info/dependency_links.txt
pyf.components.consumers.fixedlengthwriter.egg-info/entry_points.txt
pyf.components.consumers.fixedlengthwriter.egg-info/namespace_packages.txt
pyf.components.consumers.fixedlengthwriter.egg-info/requires.txt
pyf.components.consumers.fixedlengthwriter.egg-info/top_level.txt
pyf.components.consumers.fixedlengthwriter.egg-info/zip-safe
pyf/components/__init__.py
pyf/components/consumers/__init__.py
pyf/components/consumers/fixedlengthwriter/__init__.py
pyf/components/consumers/fixedlengthwriter/writer.py